Orange/__init__.py
Orange/base.py
Orange/tree.py
Orange/util.py
Orange/version.py
Orange/canvas/__init__.py
Orange/canvas/__main__.py
Orange/canvas/config.py
Orange/canvas/mainwindow.py
Orange/canvas/report.py
Orange/canvas/run.py
Orange/canvas/icons/announcement.png
Orange/canvas/icons/blog.png
Orange/canvas/icons/new-features.png
Orange/canvas/icons/orange-256.png
Orange/canvas/icons/orange-splash-screen-01.png
Orange/canvas/icons/orange-splash-screen-02.png
Orange/canvas/icons/orange-splash-screen-03.png
Orange/canvas/icons/short-survey.png
Orange/canvas/icons/statistics-request.png
Orange/canvas/icons/update.png
Orange/canvas/tests/__init__.py
Orange/canvas/tests/test_mainwindow.py
Orange/canvas/utils/__init__.py
Orange/canvas/utils/environ.py
Orange/canvas/workflows/110-file-and-data-table-widget.ows
Orange/canvas/workflows/120-scatterplot-data-table.ows
Orange/canvas/workflows/130-scatterplot-visualize-subset.ows
Orange/canvas/workflows/250-tree-scatterplot.ows
Orange/canvas/workflows/305-pca.ows
Orange/canvas/workflows/310-clustering.ows
Orange/canvas/workflows/410-feature-ranking.ows
Orange/canvas/workflows/450-cross-validation.ows
Orange/canvas/workflows/470-misclassification-scatterplot.ows
Orange/canvas/workflows/__init__.py
Orange/classification/__init__.py
Orange/classification/_simple_tree.cpython-311-aarch64-linux-gnu.so
Orange/classification/_tree_scorers.cpython-311-aarch64-linux-gnu.so
Orange/classification/base_classification.py
Orange/classification/calibration.py
Orange/classification/catgb.py
Orange/classification/gb.py
Orange/classification/knn.py
Orange/classification/logistic_regression.py
Orange/classification/majority.py
Orange/classification/naive_bayes.py
Orange/classification/neural_network.py
Orange/classification/outlier_detection.py
Orange/classification/random_forest.py
Orange/classification/rules.py
Orange/classification/scoringsheet.py
Orange/classification/sgd.py
orange3-3.40.0.dist-info/METADATA
orange3-3.40.0.dist-info/WHEEL
orange3-3.40.0.dist-info/entry_points.txt
orange3-3.40.0.dist-info/top_level.txt
orange3-3.40.0.dist-info/RECORD
orange3-3.40.0.dist-info/licenses/LICENSE
